setup.py
dnalearn/__init__.py
dnalearn/cli.py
dnalearn/dnamodel.py
dnalearn.egg-info/PKG-INFO
dnalearn.egg-info/SOURCES.txt
dnalearn.egg-info/dependency_links.txt
dnalearn.egg-info/entry_points.txt
dnalearn.egg-info/not-zip-safe
dnalearn.egg-info/requires.txt
dnalearn.egg-info/top_level.txt