Metadata-Version: 1.0
Name: dnalearn
Version: 0.2
Summary: Recommender system for sequence design and optimization
Home-page: https://github.com/tamimeur/DNAlearn.git
Author: Leli Ami
Author-email: tamimeur@gmail.com
License: MIT
Platform: UNKNOWN
